skcosmo/__init__.py
skcosmo/_selection.py
skcosmo/datasets/__init__.py
skcosmo/datasets/_base.py
skcosmo/datasets/make_csd_1000r.py
skcosmo/datasets/data/csd-1000r.npz
skcosmo/datasets/data/degenerate_CH4_manifold.npz
skcosmo/datasets/data/nice_dataset.npz
skcosmo/datasets/data/who_dataset.csv
skcosmo/datasets/descr/csd-1000r.rst
skcosmo/datasets/descr/degenerate_CH4_manifold.rst
skcosmo/datasets/descr/nice_dataset.rst
skcosmo/datasets/descr/who_dataset.rst
skcosmo/decomposition/__init__.py
skcosmo/decomposition/_kernel_pcovr.py
skcosmo/decomposition/_pcovr.py
skcosmo/feature_selection/__init__.py
skcosmo/feature_selection/_base.py
skcosmo/linear_model/__init__.py
skcosmo/linear_model/_base.py
skcosmo/linear_model/_ridge.py
skcosmo/metrics/__init__.py
skcosmo/metrics/_reconstruction_measures.py
skcosmo/model_selection/__init__.py
skcosmo/model_selection/_split.py
skcosmo/preprocessing/__init__.py
skcosmo/preprocessing/_data.py
skcosmo/sample_selection/__init__.py
skcosmo/sample_selection/_base.py
skcosmo/sample_selection/_voronoi_fps.py
skcosmo/utils/__init__.py
skcosmo/utils/_orthogonalizers.py
skcosmo/utils/_pcovr_utils.py
skcosmo/utils/_progress_bar.py
skcosmo-0.1.3.dist-info/LICENSE
skcosmo-0.1.3.dist-info/METADATA
skcosmo-0.1.3.dist-info/WHEEL
skcosmo-0.1.3.dist-info/top_level.txt
skcosmo-0.1.3.dist-info/zip-safe
skcosmo-0.1.3.dist-info/RECORD
