Metadata-Version: 2.1
Name: skcosmo
Version: 0.1.3
Summary: A collection of scikit-learn compatible utilities that implement methods developed in the COSMO laboratory
Home-page: http://scikit-cosmo.readthedocs.io
Author: Rose K. Cersonsky, Guillaume Fraux, Sergei Kliavinek, Alexander Goscinski, Benjamin A. Helfrecht, Victor P. Principe, Michele Ceriotti
Author-email: rose.cersonsky@epfl.ch
Classifier: Development Status :: 3 - Alpha
Classifier: Environment :: Console
Classifier: Intended Audience :: Science/Research
Classifier: License :: OSI Approved :: BSD License
Classifier: Natural Language :: English
Classifier: Programming Language :: Python
Classifier: Topic :: Scientific/Engineering
License-File: LICENSE
Requires-Dist: numpy
Requires-Dist: scikit-learn (>=1.1.0)
